CHANGES.rst
DESCRIPTION.rst
LICENSE
MANIFEST.in
README.md
setup.py
src/idc/pdf/__init__.py
src/idc/pdf/class_lister.py
src/idc/pdf/reader/__init__.py
src/idc/pdf/reader/_pdf.py
src/idc/pdf/writer/__init__.py
src/idc/pdf/writer/_pdf.py
src/image_dataset_converter_pdf.egg-info/PKG-INFO
src/image_dataset_converter_pdf.egg-info/SOURCES.txt
src/image_dataset_converter_pdf.egg-info/dependency_links.txt
src/image_dataset_converter_pdf.egg-info/entry_points.txt
src/image_dataset_converter_pdf.egg-info/requires.txt
src/image_dataset_converter_pdf.egg-info/top_level.txt